[{"content":"","date":"15 August 2020","permalink":"/alexleungch/alexleungch.github.io/","section":"Alex Leung","summary":"","title":"Alex Leung"},{"content":"","date":"15 August 2020","permalink":"/alexleungch/alexleungch.github.io/tags/docs/","section":"Tags","summary":"","title":"docs"},{"content":"","date":"15 August 2020","permalink":"/alexleungch/alexleungch.github.io/series/documentation/","section":"Series","summary":"","title":"Documentation"},{"content":"\rThis section assumes you have already installed the Blowfish theme.\r","date":"15 August 2020","permalink":"/alexleungch/alexleungch.github.io/technology/getting-started/","section":"Technologies","summary":"\rThis section assumes you have already installed the Blowfish theme.\r","title":"Getting Started"},{"content":"","date":"15 August 2020","permalink":"/alexleungch/alexleungch.github.io/tags/installation/","section":"Tags","summary":"","title":"installation"},{"content":"","date":"15 August 2020","permalink":"/alexleungch/alexleungch.github.io/series/","section":"Series","summary":"","title":"Series"},{"content":"","date":"15 August 2020","permalink":"/alexleungch/alexleungch.github.io/tags/","section":"Tags","summary":"","title":"Tags"},{"content":"","date":"15 August 2020","permalink":"/alexleungch/alexleungch.github.io/technology/","section":"Technologies","summary":"","title":"Technologies"},{"content":"","date":"1 January 0001","permalink":"/alexleungch/alexleungch.github.io/authors/","section":"Authors","summary":"","title":"Authors"},{"content":"","date":"1 January 0001","permalink":"/alexleungch/alexleungch.github.io/blog/","section":"Blog","summary":"","title":"Blog"},{"content":"","date":"1 January 0001","permalink":"/alexleungch/alexleungch.github.io/categories/","section":"Categories","summary":"","title":"Categories"},{"content":"","date":"1 January 0001","permalink":"/alexleungch/alexleungch.github.io/technology/","section":"Technologies","summary":"","title":"Documentation"},{"content":"","date":"1 January 0001","permalink":"/alexleungch/alexleungch.github.io/news/","section":"News","summary":"","title":"News"},{"content":"","date":"1 January 0001","permalink":"/alexleungch/alexleungch.github.io/shingeki/","section":"Shingeki","summary":"","title":"Shingeki"},{"content":"\r歡迎關注 😍\rThis section contains some demo pages that show how Blowfish renders different types of content. You can also see an example Taobao page.\nSidenote: This page is just a standard Blowfish article listing and Hugo has been configured to generate a samples content type and display article summaries.\nVersion Details 0.0.1 Personal site - Theme author ","date":"1 January 0001","permalink":"/alexleungch/alexleungch.github.io/about/","section":"關於","summary":"歡迎關注 😍\rThis section contains some demo pages that show how Blowfish renders different types of content. You can also see an example Taobao page.\nSidenote: This page is just a standard Blowfish article listing and Hugo has been configured to generate a samples content type and display article summaries.","title":"關於"}]